README.rst
boddle.py
setup.py
boddle.egg-info/PKG-INFO
boddle.egg-info/SOURCES.txt
boddle.egg-info/dependency_links.txt
boddle.egg-info/requires.txt
boddle.egg-info/top_level.txt